spock_literature/__init__.py
spock_literature/author.py
spock_literature/bot.py
spock_literature/common.py
spock_literature/main.py
spock_literature/publication.py
spock_literature/spock.py
tests/__init__.py
tests/test_spock.py
spock_literature-0.0.7.dist-info/LICENSE
spock_literature-0.0.7.dist-info/METADATA
spock_literature-0.0.7.dist-info/WHEEL
spock_literature-0.0.7.dist-info/top_level.txt
spock_literature-0.0.7.dist-info/RECORD
