Metadata-Version: 2.1
Name: spock-literature
Version: 0.0.7
Summary: A description of your package
Home-page: https://github.com/AccelerationConsortium/spock.git
Author: Youssef Briki
Author-email: youssef.briki05@gmail.com
Classifier: Programming Language :: Python :: 3
Classifier: License :: OSI Approved :: MIT License
Classifier: Operating System :: OS Independent
Requires-Python: >=3.6
License-File: LICENSE
